nrhgen/__init__.py
nrhgen/cli.py
nrhgen/hasher.py
nrhgen-0.1.0.dist-info/licenses/LICENSE
nrhgen-0.1.0.dist-info/METADATA
nrhgen-0.1.0.dist-info/WHEEL
nrhgen-0.1.0.dist-info/entry_points.txt
nrhgen-0.1.0.dist-info/top_level.txt
nrhgen-0.1.0.dist-info/RECORD
