Metadata-Version: 2.4
Name: nrhgen
Version: 0.1.0
Summary: CLI tool to generate and verify cryptographic hashes (MD5, SHA1, SHA256)
Author-email: noraraven <therealkryp10n@gmail.com>
License: MIT License
Project-URL: Homepage, https://github.com/noraraven/nrhgen
Project-URL: Source, https://github.com/noraraven/nrhgen
Requires-Python: >=3.10
License-File: LICENSE
Requires-Dist: rich>=13.3.0
Dynamic: license-file
